bioformats/__init__.py
bioformats/formatreader.py
bioformats/formatwriter.py
bioformats/logback.py
bioformats/metadatatools.py
bioformats/noseplugin.py
bioformats/omexml.py
bioformats/jars/bioformats_package.jar
python_bioformats-4.1.0.dist-info/COPYING
python_bioformats-4.1.0.dist-info/LICENSE
python_bioformats-4.1.0.dist-info/METADATA
python_bioformats-4.1.0.dist-info/WHEEL
python_bioformats-4.1.0.dist-info/top_level.txt
python_bioformats-4.1.0.dist-info/RECORD
