Metadata-Version: 2.1
Name: python-bioformats
Version: 4.1.0
Summary: Read and write life sciences file formats
Home-page: http://github.com/CellProfiler/python-bioformats/
Author: Lee Kamentsky
Author-email: leek@broadinstitute.org
License: GPL License
Classifier: Development Status :: 5 - Production/Stable
Classifier: License :: OSI Approved :: GNU General Public License v2 (GPLv2)
Classifier: Programming Language :: Python :: 2
Classifier: Programming Language :: Python :: 3
Classifier: Programming Language :: Java
Classifier: Topic :: Scientific/Engineering :: Bio-Informatics
Classifier: Topic :: Multimedia :: Graphics :: Graphics Conversion
License-File: LICENSE
License-File: COPYING
Requires-Dist: boto3 >=1.14.23
Requires-Dist: future >=0.18.2
Requires-Dist: python-javabridge ~=4.0.3
Provides-Extra: test
Requires-Dist: pytest <4,>=3.3.2 ; extra == 'test'
